CloudFlare/__init__.py
CloudFlare/api_decode_from_openapi.py
CloudFlare/api_extras.py
CloudFlare/api_v4.py
CloudFlare/cloudflare.py
CloudFlare/exceptions.py
CloudFlare/logging_helper.py
CloudFlare/network.py
CloudFlare/read_configs.py
CloudFlare/utils.py
CloudFlare/tests/__init__.py
CloudFlare/tests/dummy_loa_document.pdf
CloudFlare/tests/test_add.py
CloudFlare/tests/test_api_dump.py
CloudFlare/tests/test_certificates.py
CloudFlare/tests/test_cloudflare.py
CloudFlare/tests/test_cloudflare_calls.py
CloudFlare/tests/test_dns_import_export.py
CloudFlare/tests/test_dns_records.py
CloudFlare/tests/test_find.py
CloudFlare/tests/test_graphql.py
CloudFlare/tests/test_images_v2_direct_upload.py
CloudFlare/tests/test_ips.py
CloudFlare/tests/test_issue114.py
CloudFlare/tests/test_loa_documents.py
CloudFlare/tests/test_load_balancers.py
CloudFlare/tests/test_log_received.py
CloudFlare/tests/test_paging_thru_zones.py
CloudFlare/tests/test_purge_cache.py
CloudFlare/tests/test_radar_returning_csv.py
CloudFlare/tests/test_rulesets.py
CloudFlare/tests/test_urlscanner.py
CloudFlare/tests/test_waiting_room.py
CloudFlare/tests/test_workers.py
CloudFlare/tests/utils.py
cli4/__init__.py
cli4/__main__.py
cli4/cli4.1
cli4/cli4.py
cli4/converters.py
cli4/dump.py
cli4/examples.py
cli4/myjsonlines.py
cli4/myyaml.py
cloudflare_cli4-2.19.4.post3.dist-info/METADATA
cloudflare_cli4-2.19.4.post3.dist-info/WHEEL
cloudflare_cli4-2.19.4.post3.dist-info/entry_points.txt
cloudflare_cli4-2.19.4.post3.dist-info/licenses/LICENSE
cloudflare_cli4-2.19.4.post3.dist-info/RECORD
