Metadata-Version: 2.3
Name: cloudflare-cli4
Version: 2.19.4.post3
Summary: Command line tool to interact with Cloudflare API v4
Project-URL: documentation, https://github.com/cloudflare/python-cloudflare-cli4
Project-URL: source-code, https://github.com/cloudflare/python-cloudflare-cli4
Author-email: "Stainless Inc." <support@stainlessapi.com>, "Martin J. Levy" <mahtin@mahtin.com>
License: MIT
License-File: LICENSE
Keywords: API,cloudflare,wrapper
Classifier: Development Status :: 5 - Production/Stable
Classifier: Intended Audience :: Developers
Classifier: License :: OSI Approved :: MIT License
Classifier: Programming Language :: Python :: 3
Classifier: Programming Language :: Python :: 3 :: Only
Classifier: Programming Language :: Python :: 3.6
Classifier: Programming Language :: Python :: 3.7
Classifier: Programming Language :: Python :: 3.8
Classifier: Programming Language :: Python :: 3.9
Classifier: Programming Language :: Python :: 3.10
Classifier: Programming Language :: Python :: 3.11
Classifier: Topic :: Software Development :: Libraries :: Python Modules
Requires-Python: >3.6.0
Requires-Dist: jsonlines
Requires-Dist: pyyaml
Requires-Dist: requests
